odoo/addons/hr_contract_employee_calendar_planning/README.rst
odoo/addons/hr_contract_employee_calendar_planning/__init__.py
odoo/addons/hr_contract_employee_calendar_planning/__manifest__.py
odoo/addons/hr_contract_employee_calendar_planning/hooks.py
odoo/addons/hr_contract_employee_calendar_planning/i18n/es.po
odoo/addons/hr_contract_employee_calendar_planning/i18n/hr_contract_employee_calendar_planning.pot
odoo/addons/hr_contract_employee_calendar_planning/i18n/it.po
odoo/addons/hr_contract_employee_calendar_planning/models/__init__.py
odoo/addons/hr_contract_employee_calendar_planning/models/contract.py
odoo/addons/hr_contract_employee_calendar_planning/readme/CONTRIBUTORS.rst
odoo/addons/hr_contract_employee_calendar_planning/readme/DESCRIPTION.rst
odoo/addons/hr_contract_employee_calendar_planning/readme/USAGE.rst
odoo/addons/hr_contract_employee_calendar_planning/static/description/icon.png
odoo/addons/hr_contract_employee_calendar_planning/static/description/index.html
odoo/addons/hr_contract_employee_calendar_planning/tests/__init__.py
odoo/addons/hr_contract_employee_calendar_planning/tests/test_hr_contract_employee_calendar_planning.py
odoo/addons/hr_contract_employee_calendar_planning/views/contract.xml
odoo14_addon_hr_contract_employee_calendar_planning-14.0.1.0.1.dev8.dist-info/METADATA
odoo14_addon_hr_contract_employee_calendar_planning-14.0.1.0.1.dev8.dist-info/WHEEL
odoo14_addon_hr_contract_employee_calendar_planning-14.0.1.0.1.dev8.dist-info/top_level.txt
odoo14_addon_hr_contract_employee_calendar_planning-14.0.1.0.1.dev8.dist-info/RECORD
